dummy_socket/__init__.py
dummy_socket/exceptions.py
dummy_socket/ip_address.py
dummy_socket/whois/__init__.py
dummy_socket-0.4.dist-info/METADATA
dummy_socket-0.4.dist-info/WHEEL
dummy_socket-0.4.dist-info/top_level.txt
dummy_socket-0.4.dist-info/RECORD
