Metadata-Version: 2.1
Name: dummy-socket
Version: 0.4
Summary: simple socket programming for programmers who want to make effective programs.
Home-page: UNKNOWN
Author: Allen Sun
Author-email: allen.haha@hotmail.com
License: UNKNOWN
Platform: UNKNOWN
Classifier: Development Status :: 4 - Beta
Classifier: Programming Language :: Python :: 3
Classifier: License :: OSI Approved :: MIT License
Classifier: Operating System :: OS Independent
Requires-Python: >=3.6
Requires-Dist: python-whois (>=0.7.3)
